pierre_storage/__init__.py
pierre_storage/auth.py
pierre_storage/client.py
pierre_storage/commit.py
pierre_storage/errors.py
pierre_storage/py.typed
pierre_storage/repo.py
pierre_storage/types.py
pierre_storage/version.py
pierre_storage/webhook.py
pierre_storage-0.7.1.dist-info/licenses/LICENSE
pierre_storage-0.7.1.dist-info/METADATA
pierre_storage-0.7.1.dist-info/WHEEL
pierre_storage-0.7.1.dist-info/top_level.txt
pierre_storage-0.7.1.dist-info/RECORD
