Metadata-Version: 2.4
Name: pierre-storage
Version: 0.7.1
Summary: Pierre Git Storage SDK for Python
Author-email: Pierre <support@pierre.io>
License-Expression: MIT
Project-URL: Homepage, https://pierre.io
Project-URL: Documentation, https://docs.pierre.io
Project-URL: Repository, https://github.com/pierre/monorepo
Project-URL: Issues, https://github.com/pierre/monorepo/issues
Classifier: Development Status :: 4 - Beta
Classifier: Intended Audience :: Developers
Classifier: Programming Language :: Python :: 3
Classifier: Programming Language :: Python :: 3.8
Classifier: Programming Language :: Python :: 3.9
Classifier: Programming Language :: Python :: 3.10
Classifier: Programming Language :: Python :: 3.11
Classifier: Programming Language :: Python :: 3.12
Classifier: Topic :: Software Development :: Libraries :: Python Modules
Requires-Python: >=3.8
License-File: LICENSE
Requires-Dist: httpx>=0.27.0
Requires-Dist: pyjwt>=2.8.0
Requires-Dist: cryptography>=41.0.0
Requires-Dist: pydantic>=2.0.0
Requires-Dist: typing-extensions>=4.5.0; python_version < "3.10"
Provides-Extra: dev
Requires-Dist: pytest>=7.4.0; extra == "dev"
Requires-Dist: pytest-asyncio>=0.21.0; extra == "dev"
Requires-Dist: pytest-cov>=4.1.0; extra == "dev"
Requires-Dist: mypy>=1.5.0; extra == "dev"
Requires-Dist: ruff>=0.1.0; extra == "dev"
Requires-Dist: build>=1.0.0; extra == "dev"
Requires-Dist: twine>=4.0.0; extra == "dev"
Dynamic: license-file
